__init__.py
main.py
halodarisigma-0.1.1.dist-info/METADATA
halodarisigma-0.1.1.dist-info/WHEEL
halodarisigma-0.1.1.dist-info/top_level.txt
halodarisigma-0.1.1.dist-info/RECORD
