Metadata-Version: 2.2
Name: HALODARIsigma
Version: 0.1.1
Summary: Sigma Lab Assignment 2
Requires-Python: >=3.10
Requires-Dist: pandas>=2.2.3
